odoo/addons/ssi_account_move_line_day_overdue/README.rst
odoo/addons/ssi_account_move_line_day_overdue/__init__.py
odoo/addons/ssi_account_move_line_day_overdue/__manifest__.py
odoo/addons/ssi_account_move_line_day_overdue/data/ir_cron_data.xml
odoo/addons/ssi_account_move_line_day_overdue/models/__init__.py
odoo/addons/ssi_account_move_line_day_overdue/models/account_account.py
odoo/addons/ssi_account_move_line_day_overdue/models/account_move_line.py
odoo/addons/ssi_account_move_line_day_overdue/static/description/icon.png
odoo/addons/ssi_account_move_line_day_overdue/views/account_account_views.xml
odoo/addons/ssi_account_move_line_day_overdue/views/account_move_line_views.xml
odoo14_addon_ssi_account_move_line_day_overdue-14.0.1.1.1.dist-info/METADATA
odoo14_addon_ssi_account_move_line_day_overdue-14.0.1.1.1.dist-info/WHEEL
odoo14_addon_ssi_account_move_line_day_overdue-14.0.1.1.1.dist-info/top_level.txt
odoo14_addon_ssi_account_move_line_day_overdue-14.0.1.1.1.dist-info/RECORD
